<?xml version="1.0" encoding="utf-8" ?>
<dwsync>
<file name="dialog_sides.gif" server="203.158.140.44//home/itadmin/Payom_Game59/2559/" local="131816270243146682" remote="131702256600000000" Dst="0" />
<file name="dialog_sides.png" server="203.158.140.44//home/itadmin/Payom_Game59/2559/" local="131816270243206649" remote="131702256600000000" Dst="0" />
<file name="dialog_sides_rtl.png" server="203.158.140.44//home/itadmin/Payom_Game59/2559/" local="131816270243236629" remote="131702256600000000" Dst="0" />
<file name="mini.gif" server="203.158.140.44//home/itadmin/Payom_Game59/2559/" local="131816270243296598" remote="131702256600000000" Dst="0" />
<file name="elord.php" server="203.158.140.44//home/itadmin/Payom_Game59/2559/" local="131816270243616412" remote="131702256600000000" Dst="0" />
<file name="noimage.png" server="203.158.140.44//home/itadmin/Payom_Game59/2559/" local="131816270243626407" remote="131702256600000000" Dst="0" />
<file name="sprites.png" server="203.158.140.44//home/itadmin/Payom_Game59/2559/" local="131816270243686374" remote="131702256600000000" Dst="0" />
<file name="sprites_ie6.png" server="203.158.140.44//home/itadmin/Payom_Game59/2559/" local="131816270243706368" remote="131702256600000000" Dst="0" />
<file name="toolbar_start.gif" server="203.158.140.44//home/itadmin/Payom_Game59/2559/" local="131816270243756332" remote="131702256600000000" Dst="0" />
</dwsync>